ankix/__init__.py
ankix/ankix.py
ankix/config.py
ankix/db.py
ankix/jupyter.py
ankix/migration.py
ankix/preview.py
ankix/util.py
ankix-0.2.0.1.dist-info/LICENSE
ankix-0.2.0.1.dist-info/WHEEL
ankix-0.2.0.1.dist-info/METADATA
ankix-0.2.0.1.dist-info/RECORD
