Metadata-Version: 2.1
Name: ankix
Version: 0.2.0.1
Summary: New file format for Anki with improved review intervals and Peewee SQLite powered
Home-page: https://github.com/patarapolw/ankix
License: MIT
Keywords: anki,spaced-repetition,SRS
Author: Pacharapol Withayasakpunt
Author-email: patarapolw@gmail.com
Classifier: License :: OSI Approved :: MIT License
Classifier: Programming Language :: Python :: 2
Classifier: Programming Language :: Python :: 2.7
Classifier: Programming Language :: Python :: 3
Classifier: Programming Language :: Python :: 3.4
Classifier: Programming Language :: Python :: 3.5
Classifier: Programming Language :: Python :: 3.6
Classifier: Programming Language :: Python :: 3.7
Requires-Dist: mistune (>=0.8.4,<0.9.0)
Requires-Dist: peewee (>=3.7,<4.0)
Requires-Dist: python-magic (>=0.4.15,<0.5.0)
Requires-Dist: pytimeparse (>=1.1,<2.0)
Requires-Dist: tqdm (>=4.27,<5.0)
